README.md
setup.cfg
setup.py
python_algos.egg-info/PKG-INFO
python_algos.egg-info/SOURCES.txt
python_algos.egg-info/dependency_links.txt
python_algos.egg-info/top_level.txt
pythonalgos/__init__.py
pythonalgos/graph/__init__.py
pythonalgos/graph/algorithm_ordering.py
pythonalgos/graph/cyclic.py
pythonalgos/graph/directed_acyclic_graph.py
pythonalgos/graph/directed_graph.py
pythonalgos/graph/directed_graph_core.py
pythonalgos/graph/directed_trail.py
pythonalgos/graph/edge.py
pythonalgos/graph/kosaraju_sccs.py
pythonalgos/graph/vertex.py
pythonalgos/util/__init__.py
pythonalgos/util/advisor.py
pythonalgos/util/logging.py
pythonalgos/util/path_tools.py
tests/__init__.py
tests/graph/__init__.py
tests/graph/test_directed_acyclic_graph.py
tests/graph/test_directed_graph.py
tests/graph/test_directed_graph_cyclic.py
tests/graph/test_directed_graph_sccs.py
tests/graph/test_directed_graph_trail.py
tests/graph/test_edge.py